kintro/__init__.py
kintro/connect.py
kintro/decisions.py
kintro/kintro.py
kintro/plex.py
kintro/py.typed
kintro/utils.py
tests/__init__.py
tests/test_plex.py
kintro-0.0.1rc7.dist-info/LICENSE
kintro-0.0.1rc7.dist-info/METADATA
kintro-0.0.1rc7.dist-info/WHEEL
kintro-0.0.1rc7.dist-info/entry_points.txt
kintro-0.0.1rc7.dist-info/top_level.txt
kintro-0.0.1rc7.dist-info/RECORD
